cuemsutils/CTimecode.py
cuemsutils/CommunicatorServices.py
cuemsutils/CopyMoveVersioned.py
cuemsutils/StringSanitizer.py
cuemsutils/Uuid.py
cuemsutils/__init__.py
cuemsutils/create_script.py
cuemsutils/helpers.py
cuemsutils/log.py
cuemsutils/cues/ActionCue.py
cuemsutils/cues/AudioCue.py
cuemsutils/cues/Cue.py
cuemsutils/cues/CueList.py
cuemsutils/cues/CueOutput.py
cuemsutils/cues/CuemsScript.py
cuemsutils/cues/DmxCue.py
cuemsutils/cues/MediaCue.py
cuemsutils/cues/VideoCue.py
cuemsutils/cues/__init__.py
cuemsutils/xml/CMLCuemsConverter.py
cuemsutils/xml/Parsers.py
cuemsutils/xml/Settings.py
cuemsutils/xml/XmlBuilder.py
cuemsutils/xml/XmlReaderWriter.py
cuemsutils/xml/__init__.py
cuemsutils/xml/schemas/network_map.xsd
cuemsutils/xml/schemas/outputs.xsd
cuemsutils/xml/schemas/project_mappings.xsd
cuemsutils/xml/schemas/project_settings.xsd
cuemsutils/xml/schemas/script.xsd
cuemsutils/xml/schemas/settings.xsd
cuemsutils-0.0.8.dist-info/METADATA
cuemsutils-0.0.8.dist-info/WHEEL
cuemsutils-0.0.8.dist-info/licenses/LICENSE
cuemsutils-0.0.8.dist-info/RECORD
