Metadata-Version: 2.4
Name: cuemsutils
Version: 0.0.8
Summary: Reusable classes and methods for CueMS system
Project-URL: Documentation, https://github.com/stagesoft/cuems-utils#readme
Project-URL: Issues, https://github.com/stagesoft/cuems-utils/issues
Project-URL: Source, https://github.com/stagesoft/cuems-utils
Author-email: Adrià Masip <adria.back@gmail.com>, Ion Reguera <ion@stagelab.com>
License-Expression: GPL-3.0
License-File: LICENSE
Classifier: Development Status :: 4 - Beta
Classifier: Programming Language :: Python
Classifier: Programming Language :: Python :: 3.8
Classifier: Programming Language :: Python :: 3.9
Classifier: Programming Language :: Python :: 3.10
Classifier: Programming Language :: Python :: 3.11
Classifier: Programming Language :: Python :: 3.12
Classifier: Programming Language :: Python :: Implementation :: CPython
Classifier: Programming Language :: Python :: Implementation :: PyPy
Requires-Python: >=3.8
Requires-Dist: aiofiles==24.1.0
Requires-Dist: deprecated==1.2.18
Requires-Dist: json-fix==1.0.0
Requires-Dist: lxml==5.3.0
Requires-Dist: peewee==3.17.8
Requires-Dist: pynng==0.8.1
Requires-Dist: timecode
Requires-Dist: websockets==14.1
Requires-Dist: xmlschema==3.4.3
